{
    "version": 1,
    "projects": {
        "mappings-common-mappings": {
            "projectType": "library",
            "tsEntryPoint": "libs/mappings/common-mappings/src/index.ts",
            "importPath": "@polaris-sloc/common-mappings",
            "crds": {
                "tsConfig": "tsconfig.base.json",
                "outDir": "crds",
                "polarisTypes": [
                    "HorizontalElasticityStrategy",
                    "VerticalElasticityStrategy",
                    "CostEfficiencyMetricMapping",
                    "CostEfficiencySloMapping",
                    "CpuUsageSloMapping"
                ]
            }
        }
    }
}
